specifyplus_cli/__init__.py
syrex_specifyplus-0.0.17.dist-info/METADATA
syrex_specifyplus-0.0.17.dist-info/WHEEL
syrex_specifyplus-0.0.17.dist-info/entry_points.txt
syrex_specifyplus-0.0.17.dist-info/licenses/LICENSE
syrex_specifyplus-0.0.17.dist-info/RECORD
