Metadata-Version: 2.4
Name: syrex-specifyplus
Version: 0.0.17
Summary: SpecifyPlus CLI by Syrex Tech - A tool to bootstrap your projects for Spec-Driven Development (SDD).
License-File: LICENSE
Requires-Python: >=3.11
Requires-Dist: httpx[socks]
Requires-Dist: platformdirs
Requires-Dist: readchar
Requires-Dist: rich
Requires-Dist: truststore>=0.10.4
Requires-Dist: typer
